napalm_dellos10/__init__.py
napalm_dellos10/dellos10.py
napalm_dellos10/templates/set_hostname.j2
napalm_dellos10/utils/__init__.py
napalm_dellos10/utils/config_diff_util.py
napalm_dellos10/utils/textfsm_templates/show_version_template.tpl
napalm_dellos10-1.0.6.dist-info/DESCRIPTION.rst
napalm_dellos10-1.0.6.dist-info/METADATA
napalm_dellos10-1.0.6.dist-info/RECORD
napalm_dellos10-1.0.6.dist-info/WHEEL
napalm_dellos10-1.0.6.dist-info/metadata.json
napalm_dellos10-1.0.6.dist-info/top_level.txt
